redis_messenger/__init__.py
redis_messenger/redis_worker_API.py
redis_worker_API-0.6.1.dist-info/LICENSE
redis_worker_API-0.6.1.dist-info/METADATA
redis_worker_API-0.6.1.dist-info/WHEEL
redis_worker_API-0.6.1.dist-info/top_level.txt
redis_worker_API-0.6.1.dist-info/RECORD
