Metadata-Version: 2.1
Name: redis-worker-API
Version: 0.6.1
Summary: Library to exchange messages between workers using Redis Streams
Home-page: UNKNOWN
Author: GCP
Author-email: gonzalo.h.cordova@gmail.com
License: MIT
Platform: UNKNOWN
Classifier: Programming Language :: Python :: 3
Classifier: License :: OSI Approved :: MIT License
Classifier: Operating System :: OS Independent
Requires-Python: >=3.6
License-File: LICENSE
Requires-Dist: redis
